ruiwen_data_all/__init__.py
ruiwen_data_all-2.2.0.dist-info/METADATA
ruiwen_data_all-2.2.0.dist-info/WHEEL
ruiwen_data_all-2.2.0.dist-info/top_level.txt
ruiwen_data_all-2.2.0.dist-info/RECORD
