Metadata-Version: 2.1
Name: ruiwen-data-all
Version: 2.2.0
Requires-Dist: redis
Requires-Dist: requests
Requires-Dist: asyncio
Requires-Dist: urllib3
Requires-Dist: pymongo
Requires-Dist: w3lib
Requires-Dist: aiohttp
